stochastix/__init__.py
stochastix/_simulation_results.py
stochastix/_state_utils.py
stochastix/_stochsimsolve.py
stochastix/_systems.py
stochastix/generators.py
stochastix/analysis/__init__.py
stochastix/analysis/corr.py
stochastix/analysis/hist.py
stochastix/analysis/kde_1d.py
stochastix/analysis/kde_2d.py
stochastix/analysis/mi.py
stochastix/controllers/__init__.py
stochastix/controllers/_base.py
stochastix/controllers/_timer.py
stochastix/kinetics/__init__.py
stochastix/kinetics/_base.py
stochastix/kinetics/_hill.py
stochastix/kinetics/_hill2d.py
stochastix/kinetics/_massaction.py
stochastix/kinetics/_mm.py
stochastix/kinetics/_nn.py
stochastix/reaction/__init__.py
stochastix/reaction/_network.py
stochastix/reaction/_reaction.py
stochastix/solvers/__init__.py
stochastix/solvers/_approximate.py
stochastix/solvers/_base.py
stochastix/solvers/_differentiable.py
stochastix/solvers/_exact.py
stochastix/utils/__init__.py
stochastix/utils/_utils.py
stochastix/utils/nn.py
stochastix/utils/visualization.py
stochastix/utils/optimization/__init__.py
stochastix/utils/optimization/_grad.py
stochastix/utils/optimization/_losses.py
stochastix/utils/optimization/_rewards.py
stochastix/utils/optimization/_utils.py
stochastix-0.1.0.dist-info/METADATA
stochastix-0.1.0.dist-info/WHEEL
stochastix-0.1.0.dist-info/licenses/LICENSE
stochastix-0.1.0.dist-info/RECORD
