Metadata-Version: 2.4
Name: stochastix
Version: 0.1.0
Summary: Differentiable, hardware accelerated (stochastic) kinetic models in JAX.
Project-URL: Homepage, https://github.com/fmottes/stochastix
Project-URL: Repository, https://github.com/fmottes/stochastix
Project-URL: Documentation, https://fmottes.github.io/stochastix/
Author-email: Francesco Mottes <fmottes@seas.harvard.edu>
License:                                  Apache License
License-File: LICENSE
Keywords: differentiable,gillespie,jax,kinetic-models,simulation,ssa,stochastic,systems-biology
Classifier: Development Status :: 4 - Beta
Classifier: Intended Audience :: Developers
Classifier: Intended Audience :: Science/Research
Classifier: License :: OSI Approved :: Apache Software License
Classifier: Natural Language :: English
Classifier: Operating System :: OS Independent
Classifier: Programming Language :: Python :: 3
Classifier: Topic :: Scientific/Engineering :: Artificial Intelligence
Classifier: Topic :: Scientific/Engineering :: Bio-Informatics
Classifier: Topic :: Scientific/Engineering :: Mathematics
Requires-Python: <4.0,>=3.10
Requires-Dist: diffrax>=0.7.0
Requires-Dist: equinox>=0.12.2
Requires-Dist: jax>=0.6.2
Requires-Dist: matplotlib>=3.9.1
Provides-Extra: notebooks
Requires-Dist: ipykernel>=6.30.0; extra == 'notebooks'
Requires-Dist: optax>=0.2.5; extra == 'notebooks'
Requires-Dist: tqdm>=4.67.1; extra == 'notebooks'
